[
    {
        "id": "M001",
        "category": "マネジメント系",
        "subcategory": "開発技術",
        "topic": "システム開発技術",
        "difficulty": 1,
        "question": "ウォータフォールモデルの特徴として、適切なものはどれか。",
        "choices": {
            "ア": "開発チームが自律的に作業を管理し、短いスプリントで成果物を作る。",
            "イ": "短い開発サイクルを繰り返してシステムを段階的に完成させる。",
            "ウ": "プロトタイプを作成してユーザーの確認を得ながら開発を進める。",
            "エ": "各工程を順番に進め、前の工程が完了してから次の工程に移る。"
        },
        "answer": "エ",
        "explanation": "ウォータフォールモデルは、要件定義→設計→実装→テスト→運用保守の各工程を上流から下流へ順番に進める開発手法です。水が上から下に流れるように後戻りしないことが原則です。イはエジャイル開発、ウはプロトタイピングモデル、アはスクラムの特徴です。"
    },
    {
        "id": "M002",
        "category": "マネジメント系",
        "subcategory": "開発技術",
        "topic": "システム開発技術",
        "difficulty": 2,
        "question": "アジャイル開発の特徴として、最も適切なものはどれか。",
        "choices": {
            "ア": "短い期間で動作するソフトウェアを反復的にリリースする。",
            "イ": "開発の初期段階で詳細な設計書を完成させる。",
            "ウ": "最初にすべての要件を詳細に定義してから開発を始める。",
            "エ": "開発工程の各段階でレビューを行い、次の工程に進む承認を得る。"
        },
        "answer": "ア",
        "explanation": "アジャウル開発は、短い反復（ウテレーション）を繰り返し、顧客のフィードバックを取り入れながら、動作するソフトエェアを段階的に提供する開発手法です。変化への対応を重視し、最初にすべてを決めるのではなく、柔軟に進めます。"
    },
    {
        "id": "M003",
        "category": "マネジメント系",
        "subcategory": "開発技術",
        "topic": "システム開発技術",
        "difficulty": 2,
        "question": "システム開発の工程において、ソフトウェアが要件定義どおりに動作することを発注者が確認するテストはどれか。",
        "choices": {
            "ア": "単体テスト",
            "イ": "受入テスト（承認テスト）",
            "ウ": "結合テスト",
            "エ": "システムテスト"
        },
        "answer": "イ",
        "explanation": "受入テスト（承認テスト）は、システムの発注者（ユーザー）が行うテストで、開発されたシステムが要件定義どおりに動作するかを確認します。単体テストは個々のモジュール、結合テストはモジュール間の連携、システムテストはシステム全体の動作を確認します。"
    },
    {
        "id": "M004",
        "category": "マネジメント系",
        "subcategory": "開発技術",
        "topic": "システム開発技術",
        "difficulty": 2,
        "question": "ブラックボックステストの説明として、適切なものはどれか。",
        "choices": {
            "ア": "プログラムの内部構造を意識せず、入力と出力の関係で正しさを検証する。",
            "イ": "開発者がプログラム作成と同時にテストケースを作成する。",
            "ウ": "ユーザーが実際の運用環境でテストを実施する。",
            "エ": "プログラムの内部構造に基づいて、すべての分岐経路を検証する。"
        },
        "answer": "ア",
        "explanation": "ブラックボックステストは、プログラムの内部構造を考慮せず、入力データに対する出力結果が仕様通りかを検証するテスト手法です。エはホワエトボックステスト（内部構造を確認するテスト）の説明です。"
    },
    {
        "id": "M005",
        "category": "マネジメント系",
        "subcategory": "開発技術",
        "topic": "ソフトウェア開発管理技術",
        "difficulty": 2,
        "question": "DevOpsの説明として、適切なものはどれか。",
        "choices": {
            "ア": "外部のクラウドサービスを利用して開発環境を構築する手法",
            "イ": "開発プロジェクトを複数のフェーズに分けて段階的にリリースする手法",
            "ウ": "開発（Development）と運用（Operations）が連携・協力し、迅速かつ安定したシステム提供を実現する手法",
            "エ": "運用部門がシステムの開発も担当し、一元管理する手法"
        },
        "answer": "ウ",
        "explanation": "DevOpsは、開発チーム（Dev）と運用チーム（Ops）が密に連携し、自動化ツールやCI/CDパイプラインを活用して、ソフトエェウの開発からリリース、運用までのサイクルを迅速化する文化・手法です。"
    },
    {
        "id": "M006",
        "category": "マネジメント系",
        "subcategory": "開発技術",
        "topic": "システム開発技術",
        "difficulty": 2,
        "question": "リファクタリングの説明として、適切なものはどれか。",
        "choices": {
            "ア": "古いプログラミング言語で書かれたシステムを新しい言語に書き換えること",
            "イ": "障害が発生したプログラムを修正して復旧すること",
            "ウ": "外部から見た動作を変えずに、プログラムの内部構造を改善すること",
            "エ": "新しい機能を追加するためにプログラムを修正すること"
        },
        "answer": "ウ",
        "explanation": "リファクタリングとは、ソフトイェウの外部的な動作（機能）を変更せずに、ソースコードの内部構造を整理・改善する活動です。コードの可読性、保守性、拡張性の向上を目的としています。"
    },
    {
        "id": "M007",
        "category": "マネジメント系",
        "subcategory": "プロジェクトマネジメント",
        "topic": "プロジェクトマネジメント手法",
        "difficulty": 1,
        "question": "WBS（Work Breakdown Structure）の説明として、適切なものはどれか。",
        "choices": {
            "ア": "プロジェクトの進捗状況を折れ線グラフで表したもの",
            "イ": "プロジェクトの作業を階層的に分解して構造化したもの",
            "ウ": "プロジェクトのメンバーの役割と責任を定義したもの",
            "エ": "プロジェクトのリスクを洗い出して一覧にしたもの"
        },
        "answer": "イ",
        "explanation": "WBS（作業分解構成図）は、プロジェクトの全体作業を階層的に詳細な作業単位（ワークパッケージ）に分解し、ツリー構造で表したものです。プロジェクトのスコープを明確にし、作業の漏れを防ぎ、スケジュールやコストの見積りの基礎資料となります。"
    },
    {
        "id": "M008",
        "category": "マネジメント系",
        "subcategory": "プロジェクトマネジメント",
        "topic": "プロジェクトマネジメント手法",
        "difficulty": 2,
        "question": "ガントチャートの説明として、適切なものはどれか。",
        "choices": {
            "ア": "プロジェクトの成果物を階層的に分解して構造化した図",
            "イ": "作業間の依存関係をネットワーク図で表し、クリティカルパスを明確にした図",
            "ウ": "作業項目を縦軸に、時間を横軸にとり、各作業の開始・終了・進捗状況を棒グラフで示した図",
            "エ": "プロジェクトのコストの予算と実績を時間軸で比較した図"
        },
        "answer": "ウ",
        "explanation": "ガントチャートは、プロジェクトの各作業の開始日・終了日・進捗状況を横棒で視覚的に表す図です。作業の並行状況や全体のスケジュールを把握しやすい特徴があります。イはPERT図（ウローダイウグラム）の説明です。"
    },
    {
        "id": "M009",
        "category": "マネジメント系",
        "subcategory": "プロジェクトマネジメント",
        "topic": "プロジェクトマネジメント手法",
        "difficulty": 2,
        "question": "クリティカルパスの説明として、適切なものはどれか。",
        "choices": {
            "ア": "プロジェクトの各作業の中で、最もコストがかかる作業の経路",
            "イ": "プロジェクトの各作業の中で、最も人員が必要な作業の経路",
            "ウ": "プロジェクトの各作業の中で、最もリスクが高い作業の経路",
            "エ": "プロジェクト全体の所要期間を決定する、最も長い経路"
        },
        "answer": "エ",
        "explanation": "クリティカルパスは、プロジェクトのネットワーク図（PERT図等）において、開始から完了までの経路のうち最も所要時間が長い経路です。この経路上の作業が遅れると、プロジェクト全体の完了が遅れます。余裕日数（フロート）がゼロの経路とも言えます。"
    },
    {
        "id": "M010",
        "category": "マネジメント系",
        "subcategory": "プロジェクトマネジメント",
        "topic": "プロジェクトマネジメント手法",
        "difficulty": 3,
        "question": "ファンクションポイント法の説明として、適切なものはどれか。",
        "choices": {
            "ア": "開発対象のプログラムの行数（ステップ数）に基づいて開発規模を見積もる方法",
            "イ": "開発メンバーの経験と勘に基づいて開発規模を見積もる方法",
            "ウ": "ソフトウェアの機能の数と複雑さに基づいて開発規模を見積もる方法",
            "エ": "過去の類似プロジェクトの実績データに基づいて開発規模を見積もる方法"
        },
        "answer": "ウ",
        "explanation": "ファンクションポエント法は、外部入力、外部出力、内部論理ファエル、外部エンタフェースファエル、外部照会の5つの機能の種類と複雑さに基づいてソフトアェウの規模を見積もる手法です。エは類推見積り法、アはLOC法（ステップ法）の説明です。"
    },
    {
        "id": "M011",
        "category": "マネジメント系",
        "subcategory": "プロジェクトマネジメント",
        "topic": "プロジェクトマネジメント手法",
        "difficulty": 2,
        "question": "プロジェクトにおけるステークホルダの説明として、適切なものはどれか。",
        "choices": {
            "ア": "プロジェクトの予算を承認する経営者のみ",
            "イ": "プロジェクトに影響を与えたり、影響を受けたりするすべての関係者",
            "ウ": "プロジェクトの実際の開発作業を行うメンバーのみ",
            "エ": "プロジェクトの成果物を利用するエンドユーザーのみ"
        },
        "answer": "イ",
        "explanation": "ステークホルダとは、プロジェクトの計画や遂行に何らかの影響を与えたり、あるいは影響を受けたりするすべての関係者を指します。プロジェクトマネージャー、開発メンバー、発注者、エンドユーザー、経営者、株主など幅広い人々が含まれます。"
    },
    {
        "id": "M012",
        "category": "マネジメント系",
        "subcategory": "サービスマネジメント",
        "topic": "サービスマネジメントシステム",
        "difficulty": 2,
        "question": "ITIL（Information Technology Infrastructure Library）の説明として、適切なものはどれか。",
        "choices": {
            "ア": "プロジェクトマネジメントの知識体系",
            "イ": "ITサービスマネジメントのベストプラクティスをまとめたフレームワーク",
            "ウ": "ソフトウェア開発の成熟度をレベルで評価するモデル",
            "エ": "情報セキュリティマネジメントの国際規格"
        },
        "answer": "イ",
        "explanation": "ITILは、ITサービスの提供・管理に関するベストプラクティス（成功事例）を体系的にまとめたフレームワークです。エはISO 27001（ISMS）、ウはCMMI、アはPMBOKの説明です。"
    },
    {
        "id": "M013",
        "category": "マネジメント系",
        "subcategory": "サービスマネジメント",
        "topic": "サービスの運用",
        "difficulty": 2,
        "question": "インシデント管理の目的として、適切なものはどれか。",
        "choices": {
            "ア": "ITサービスの中断や品質低下を迅速に回復し、ビジネスへの影響を最小限にする。",
            "イ": "インシデントの根本原因を究明し、再発を防止する。",
            "ウ": "ITサービスの変更を適切に管理し、障害の発生を防ぐ。",
            "エ": "ITシステムの構成要素を正確に把握し、管理する。"
        },
        "answer": "ア",
        "explanation": "インシデント管理の目的は、発生したインシデント（ITサービスの中断や品質低下）を可能な限り迅速に解決し、通常のサービス運用を回復することです。イは問題管理、エは構成管理、ウは変更管理の目的です。"
    },
    {
        "id": "M014",
        "category": "マネジメント系",
        "subcategory": "サービスマネジメント",
        "topic": "サービスの運用",
        "difficulty": 2,
        "question": "SLA（Service Level Agreement）の説明として、適切なものはどれか。",
        "choices": {
            "ア": "情報セキュリティに関するポリシーを定めた文書",
            "イ": "障害発生時の対応手順を定めた運用マニュアル",
            "ウ": "システム開発の費用と納期を定めた契約書",
            "エ": "ITサービスの提供者と顧客の間で合意した、サービスの品質水準を定めた文書"
        },
        "answer": "エ",
        "explanation": "SLA（サービスレベル合意書）は、ITサービスの提供者と利用者（顧客）の間で、サービスの可用性、応答時間、障害復旧時間などの品質水準を定めた合意文書です。サービスの品質目標を明確にし、双方の責任範囲を明らかにします。"
    },
    {
        "id": "M015",
        "category": "マネジメント系",
        "subcategory": "サービスマネジメント",
        "topic": "サービスの運用",
        "difficulty": 2,
        "question": "ヘルプデスク（サービスデスク）の機能として、最も適切なものはどれか。",
        "choices": {
            "ア": "ユーザーからの問合せや障害報告を一元的に受け付け、対応する窓口",
            "イ": "新規システムの企画・提案を行う部門",
            "ウ": "システムの設計書や仕様書を管理する部門",
            "エ": "システムのセキュリティ監視を24時間行う専門チーム"
        },
        "answer": "ア",
        "explanation": "サービスデスク（ヘルプデスク）は、ユーザーからの問合せ、障害報告、サービス要求などを受け付ける単一の窓口（SPOC: Single Point of Contact）として機能します。ITILにおけるサービスオペレーションの重要な機能です。"
    },
    {
        "id": "M016",
        "category": "マネジメント系",
        "subcategory": "サービスマネジメント",
        "topic": "ファシリティマネジメント",
        "difficulty": 2,
        "question": "UPS（Uninterruptible Power Supply）の説明として、適切なものはどれか。",
        "choices": {
            "ア": "停電時にもコンピュータに一時的に電力を供給し、安全にシャットダウンするための装置",
            "イ": "通信回線の帯域を増幅して通信速度を向上させる装置",
            "ウ": "サーバルームの温度を一定に保つための空調設備",
            "エ": "外部からの不正アクセスを遮断するためのセキュリティ機器"
        },
        "answer": "ア",
        "explanation": "UPS（無停電電源装置）は、停電や瞬断が発生した際に蓄電池（バッテリー）から電力を供給し、コンピュータやサーバーが安全にシャットダウンできるようにする装置です。データの消失やハードウェアの損傷を防止します。"
    },
    {
        "id": "M017",
        "category": "マネジメント系",
        "subcategory": "システム監査",
        "topic": "システム監査",
        "difficulty": 2,
        "question": "システム監査の目的として、適切なものはどれか。",
        "choices": {
            "ア": "情報システムが適切に管理・運用されているかを独立した立場から評価し、改善を助言する。",
            "イ": "情報システムの利用者に対して教育・訓練を行う。",
            "ウ": "情報システムの開発進捗を管理し、納期通りにリリースする。",
            "エ": "情報システムのセキュリティ対策を実施する。"
        },
        "answer": "ア",
        "explanation": "システム監査は、独立かつ客観的な立場から、情報システムの信頼性・安全性・効率性を点検・評価し、問題点があれば改善のための助言・勧告を行う活動です。監査人は被監査部門から独立している必要があります。"
    },
    {
        "id": "M018",
        "category": "マネジメント系",
        "subcategory": "システム監査",
        "topic": "内部統制",
        "difficulty": 2,
        "question": "内部統制の目的に含まれないものはどれか。",
        "choices": {
            "ア": "業務の有効性と効率性の確保",
            "イ": "財務報告の信頼性の確保",
            "ウ": "法令の遵守",
            "エ": "市場シェアの拡大"
        },
        "answer": "エ",
        "explanation": "内部統制の4つの目的は、①業務の有効性と効率性、②財務報告の信頼性、③事業活動に関わる法令等の遵守、④資産の保全です。市場シェエの拡大は経営戦略の目標であり、内部統制の目的には含まれません。"
    },
    {
        "id": "M019",
        "category": "マネジメント系",
        "subcategory": "開発技術",
        "topic": "システム開発技術",
        "difficulty": 2,
        "question": "スクラムにおけるスプリントの説明として、適切なものはどれか。",
        "choices": {
            "ア": "一定期間（通常1〜4週間）の反復単位で、その期間内に計画した作業を完了させる。",
            "イ": "テスト工程だけを集中的に行う特別な期間のこと。",
            "ウ": "プロジェクト全体の工程を一つのまとまりとして管理する。",
            "エ": "システム障害が発生した際に緊急対応を行う期間のこと。"
        },
        "answer": "ア",
        "explanation": "スプリントは、スクラム（アジャウル開発手法の一つ）における固定長の反復単位（タウムボックス）です。通常1〜4週間で設定され、スプリント計画で選択された作業（バックログアウテム）を完了させることを目指します。"
    },
    {
        "id": "M020",
        "category": "マネジメント系",
        "subcategory": "プロジェクトマネジメント",
        "topic": "プロジェクトマネジメント手法",
        "difficulty": 2,
        "question": "EVM（Earned Value Management）で使用される指標のうち、プロジェクトのコスト効率を示す指標はどれか。",
        "choices": {
            "ア": "SPI（Schedule Performance Index）",
            "イ": "PV（Planned Value）",
            "ウ": "EAC（Estimate At Completion）",
            "エ": "CPI（Cost Performance Index）"
        },
        "answer": "エ",
        "explanation": "CPI（コスト効率指数）は、EV（出来高）÷ AC（実コスト）で計算されるコスト効率の指標です。CPI > 1ならコスト効率が良好、CPI < 1ならコスト超過を意味します。SPI はスケジュール効率、PVは計画価値、EACは完了時の総コスト推定額です。"
    },
    {
        "id": "M021",
        "category": "マネジメント系",
        "subcategory": "サービスマネジメント",
        "topic": "サービスマネジメントシステム",
        "difficulty": 2,
        "question": "可用性の説明として、適切なものはどれか。",
        "choices": {
            "ア": "システムのセキュリティが確保されている状態のこと",
            "イ": "システムの処理能力が需要に追いつかない状態のこと",
            "ウ": "システムが正常に稼働し、利用可能である割合や時間のこと",
            "エ": "システムが障害から復旧するまでの平均時間のこと"
        },
        "answer": "ウ",
        "explanation": "可用性（ウベエラビリティ）は、システムが正常に稼働していて利用可能である度合いを示す指標です。稼働率で表され、稼働率 = MTBF ÷（MTBF + MTTR）で計算されます。MTBF（平均故障間隔）が長く、MTTR（平均修理時間）が短いほど可用性が高くなります。"
    },
    {
        "id": "M022",
        "category": "マネジメント系",
        "subcategory": "開発技術",
        "topic": "システム開発技術",
        "difficulty": 2,
        "question": "結合テストの目的として、適切なものはどれか。",
        "choices": {
            "ア": "個々のモジュール単体が設計どおりに動作するかを確認する。",
            "イ": "開発されたシステムが利用者の業務に適合するかを確認する。",
            "ウ": "システム全体が要件定義どおりに動作するかを確認する。",
            "エ": "複数のモジュールを組み合わせたとき、モジュール間のインタフェースが正しく機能するかを確認する。"
        },
        "answer": "エ",
        "explanation": "結合テスト（統合テスト）は、単体テスト済みの複数のモジュールを組み合わせて、モジュール間のアンタフェース（データの受け渡しや呼び出し）が正しく動作するかを検証するテストです。アは単体テスト、ウはシステムテスト、イは受入テストの目的です。"
    },
    {
        "id": "M023",
        "category": "マネジメント系",
        "subcategory": "プロジェクトマネジメント",
        "topic": "プロジェクトマネジメント手法",
        "difficulty": 2,
        "question": "PMBOK（Project Management Body of Knowledge）が定義するプロジェクトマネジメントの知識エリアに含まれないものはどれか。",
        "choices": {
            "ア": "セールスマネジメント",
            "イ": "コストマネジメント",
            "ウ": "リスクマネジメント",
            "エ": "スコープマネジメント"
        },
        "answer": "ア",
        "explanation": "PMBOKの知識ウリアには、統合、スコープ、スケジュール、コスト、品質、資源、コミュニケーション、リスク、調達、ステークホルダーの10の知識ウリアがあります。「セールスマネジメント」は含まれていません。"
    },
    {
        "id": "M024",
        "category": "マネジメント系",
        "subcategory": "サービスマネジメント",
        "topic": "サービスの運用",
        "difficulty": 2,
        "question": "変更管理の目的として、適切なものはどれか。",
        "choices": {
            "ア": "障害発生時に迅速にサービスを復旧させる。",
            "イ": "サービスの利用料金を適切に設定する。",
            "ウ": "ITサービスやインフラへの変更を適切に管理し、変更に伴うリスクを最小限にする。",
            "エ": "ITサービスの利用状況を監視し、キャパシティの過不足を把握する。"
        },
        "answer": "ウ",
        "explanation": "変更管理は、ITサービスやITエンフラに対する変更要求を受け付け、その変更がもたらす影響やリスクを適切に評価・承認し、計画的に実施する管理プロセスです。変更による障害発生やサービス低下を防止することが目的です。"
    },
    {
        "id": "M025",
        "category": "マネジメント系",
        "subcategory": "システム監査",
        "topic": "システム監査",
        "difficulty": 2,
        "question": "システム監査人に求められる独立性の説明として、適切なものはどれか。",
        "choices": {
            "ア": "監査対象の業務に精通し、改善策を実行する能力がある。",
            "イ": "監査対象から独立した立場で、客観的に監査を実施する。",
            "ウ": "システムの開発経験が豊富で、技術的な知識が高い。",
            "エ": "経営者の指示に従って監査を実施する。"
        },
        "answer": "イ",
        "explanation": "システム監査人には、被監査部門から独立した立場（組織的独立性・精神的独立性）で、客観的かつ公正に監査を行うことが求められます。監査の信頼性を確保するために、監査対象の部門に所属していない人が監査を実施する必要があります。"
    },
    {
        "id": "M026",
        "category": "マネジメント系",
        "subcategory": "開発技術",
        "topic": "ソフトウェア開発管理技術",
        "difficulty": 2,
        "question": "CI/CD（継続的インテグレーション/継続的デリバリー）の説明として、適切なものはどれか。",
        "choices": {
            "ア": "コードの変更を頻繁に統合し、自動テスト・自動デプロイを行うことで、品質を保ちながら迅速にリリースする手法",
            "イ": "運用部門が手動でコードをデプロイし、品質を確認する手法",
            "ウ": "プロジェクトの開始前に全ての要件を確定し、一括でリリースする手法",
            "エ": "開発完了後にまとめてテストを行い、問題がなければデプロイする手法"
        },
        "answer": "ア",
        "explanation": "CI（継続的ウンテグレーション）は、開発者が頻繁にコードを共有リポジトリに統合し、自動ビルド・自動テストで品質を確認する手法です。CD（継続的デリバリー/デプロウメント）は、テスト済みのコードを自動的に本番環境へデプロウする手法です。DevOpsの重要な構成要素です。"
    },
    {
        "id": "M027",
        "category": "マネジメント系",
        "subcategory": "サービスマネジメント",
        "topic": "サービスの運用",
        "difficulty": 2,
        "question": "問題管理とインシデント管理の違いとして、適切なものはどれか。",
        "choices": {
            "ア": "インシデント管理と問題管理は同じ目的で行われるが、担当者が異なる。",
            "イ": "インシデント管理は予防的な活動であり、問題管理は事後対応の活動である。",
            "ウ": "インシデント管理はサービスの迅速な復旧を目的とし、問題管理はインシデントの根本原因の究明と再発防止を目的とする。",
            "エ": "インシデント管理は長期的な対策を行い、問題管理は短期的な応急処置を行う。"
        },
        "answer": "ウ",
        "explanation": "エンシデント管理はサービスの迅速な復旧（応急処置）に焦点を当て、問題管理はエンシデントの根本原因（Root Cause）を特定し、恒久的な対策を講じて再発を防止することに焦点を当てます。両者は補完的な関係にあります。"
    },
    {
        "id": "M028",
        "category": "マネジメント系",
        "subcategory": "開発技術",
        "topic": "システム開発技術",
        "difficulty": 2,
        "question": "レビュー手法の一つであるウォークスルーの説明として、適切なものはどれか。",
        "choices": {
            "ア": "統計的なサンプリングにより、成果物の品質を検証するレビュー手法",
            "イ": "モデレータが進行役を務め、チェックリストに基づいて厳密に欠陥を検出するレビュー手法",
            "ウ": "レビュー対象の成果物を参加者が個別に確認し、個々にコメントを提出するレビュー手法",
            "エ": "作成者が成果物の内容を参加者に説明しながら、問題点を指摘してもらうレビュー手法"
        },
        "answer": "エ",
        "explanation": "ウォークスルーは、作成者が主導して成果物（設計書やコードなど）を参加者に説明し、参加者が質問や指摘を行う非公式なレビュー手法です。イはインスペクション（最も公式で厳密なレビュー）の説明です。"
    },
    {
        "id": "M029",
        "category": "マネジメント系",
        "subcategory": "プロジェクトマネジメント",
        "topic": "プロジェクトマネジメント手法",
        "difficulty": 2,
        "question": "プロジェクトのリスク対応策のうち、「回避」の説明として適切なものはどれか。",
        "choices": {
            "ア": "リスクの影響を第三者に移転する（例：保険への加入）。",
            "イ": "リスクの原因を取り除き、リスクが発生しないようにする。",
            "ウ": "リスクの存在を認識した上で、何も対策を取らずに受け入れる。",
            "エ": "リスクの発生確率や影響度を下げるための対策を講じる。"
        },
        "answer": "イ",
        "explanation": "リスク対応策には4つのカテゴリがあります。回避はリスクの原因自体を取り除くこと、転嫁（ア）はリスクを第三者に移すこと、軽減（エ）は発生確率や影響を小さくすること、受容（ウ）はリスクを認識しつつ対応しないことです。"
    },
    {
        "id": "M030",
        "category": "マネジメント系",
        "subcategory": "システム監査",
        "topic": "内部統制",
        "difficulty": 2,
        "question": "ITガバナンスの説明として、適切なものはどれか。",
        "choices": {
            "ア": "システム開発における品質管理の基準を定めた規格",
            "イ": "外部の監査法人がIT投資の妥当性を評価する仕組み",
            "ウ": "情報システム部門がサーバやネットワークの運用を管理する仕組み",
            "エ": "経営陣がIT戦略の策定と実行を指導・管理し、ITが経営目標の達成に貢献するよう統制する仕組み"
        },
        "answer": "エ",
        "explanation": "ITガバナンスとは、経営陣がリーダーシップを発揮し、IT戦略の策定・実行を指導・管理することで、ITが企業の事業目標の達成に寄与するよう統制・評価する仕組みです。JIS Q 38500（ISO/IEC 38500）で定義されています。"
    },
    {
        "id": "M031",
        "category": "マネジメント系",
        "subcategory": "サービスマネジメント",
        "topic": "サービスの運用",
        "difficulty": 2,
        "question": "構成管理の目的として、適切なものはどれか。",
        "choices": {
            "ア": "障害発生時にサービスを迅速に復旧する。",
            "イ": "新しいサービスを本番環境に展開する。",
            "ウ": "ITインフラを構成するハードウェア、ソフトウェア、文書などの構成情報を正確に把握し管理する。",
            "エ": "変更要求を評価し承認する。"
        },
        "answer": "ウ",
        "explanation": "構成管理は、ITサービスを構成するCI（Configuration Item：構成ウアテム）の情報を正確に記録・管理するプロセスです。ハードエェウ、ソフトエェウ、ネットワーク機器、ドキュメントなどの構成情報をCMDB（構成管理データベース）で一元管理します。"
    },
    {
        "id": "M032",
        "category": "マネジメント系",
        "subcategory": "サービスマネジメント",
        "topic": "サービスの運用",
        "difficulty": 2,
        "question": "リリース管理の目的として、適切なものはどれか。",
        "choices": {
            "ア": "サービスの利用状況を分析し、将来の需要を予測する。",
            "イ": "サービスの可用性を監視し、稼働率を向上させる。",
            "ウ": "インシデントの根本原因を特定し、恒久的な対策を実施する。",
            "エ": "新規または変更されたサービスを、品質を確保しながら本番環境に展開する。"
        },
        "answer": "エ",
        "explanation": "リリース管理は、テスト済みの新規・変更コンポーネントを本番環境に安全かつ計画的に展開（リリース）するプロセスです。リリースの計画、テスト、承認、配布、導入を管理し、サービスの品質と安定性を確保します。"
    },
    {
        "id": "M033",
        "category": "マネジメント系",
        "subcategory": "プロジェクトマネジメント",
        "topic": "プロジェクトマネジメント手法",
        "difficulty": 2,
        "question": "プロジェクトのスコープの説明として、適切なものはどれか。",
        "choices": {
            "ア": "プロジェクトで実現すべき成果物や作業の範囲",
            "イ": "プロジェクトの予算の総額",
            "ウ": "プロジェクトの開始日から終了日までの期間",
            "エ": "プロジェクトに参加するメンバーの人数"
        },
        "answer": "ア",
        "explanation": "スコープとは、プロジェクトで何を作るか（プロダクトスコープ）、どのような作業を行うか（プロジェクトスコープ）という範囲のことです。スコープを明確に定義することで、要求の追加（スコープクリープ）を防ぎ、プロジェクトを成功に導きます。"
    },
    {
        "id": "M034",
        "category": "マネジメント系",
        "subcategory": "開発技術",
        "topic": "ソフトウェア開発管理技術",
        "difficulty": 2,
        "question": "テスト駆動開発（TDD）の説明として、適切なものはどれか。",
        "choices": {
            "ア": "開発完了後にまとめてテストを実施する開発手法",
            "イ": "テストコードを先に書き、そのテストを通過するプログラムコードを後から書く開発手法",
            "ウ": "ユーザーインタフェースのテストだけを重点的に行う開発手法",
            "エ": "テスト専門のチームが独立してテストを行う開発手法"
        },
        "answer": "イ",
        "explanation": "テスト駆動開発（TDD: Test-Driven Development）は、最初に失敗するテストを書き（Red）、テストを通過するための最小限のコードを書き（Green）、コードを整理する（Refactor）というサアクルを繰り返す開発手法です。イジャアル開発でよく用いられます。"
    },
    {
        "id": "M035",
        "category": "マネジメント系",
        "subcategory": "サービスマネジメント",
        "topic": "サービスマネジメントシステム",
        "difficulty": 2,
        "question": "キャパシティ管理の目的として、適切なものはどれか。",
        "choices": {
            "ア": "現在および将来のビジネス要求に対して、適切なITリソースを適切なコストで提供できるようにする。",
            "イ": "ITシステムのセキュリティを確保する。",
            "ウ": "ITサービスの変更をリスクを最小限にして実施する。",
            "エ": "障害発生時にITサービスを迅速に復旧する。"
        },
        "answer": "ア",
        "explanation": "キャパシティ管理は、ITサービスに必要なリソース（CPU、メモリ、ストレージ、ネットワーク帯域等）が、現在および将来の需要に対して適切に確保されるよう計画・管理するプロセスです。過剰投資と性能不足の両方を防ぎます。"
    },
    {
        "id": "M036",
        "category": "マネジメント系",
        "subcategory": "開発技術",
        "topic": "システム開発技術",
        "difficulty": 2,
        "question": "ペアプログラミングの説明として、適切なものはどれか。",
        "choices": {
            "ア": "開発とテストを2人で分担して行う手法",
            "イ": "2種類のプログラミング言語を使って同じシステムを開発する手法",
            "ウ": "2人のプログラマが1台のコンピュータを共有し、一方がコードを書き、もう一方がリアルタイムでレビューする手法",
            "エ": "2つのチームが同じ機能を別々に開発し、品質の高い方を採用する手法"
        },
        "answer": "ウ",
        "explanation": "ペウプログラミングは、アクストリームプログラミング（XP）のプラクティスの一つで、ドラエバー（コードを書く人）とナビゲーター（レビュー・助言する人）の2人が一組となってプログラミングを行う手法です。コード品質の向上と知識の共有に効果的です。"
    },
    {
        "id": "M037",
        "category": "マネジメント系",
        "subcategory": "プロジェクトマネジメント",
        "topic": "プロジェクトマネジメント手法",
        "difficulty": 2,
        "question": "プロジェクトにおけるマイルストーンの説明として、適切なものはどれか。",
        "choices": {
            "ア": "プロジェクトで使用するツールやソフトウェア",
            "イ": "プロジェクトの主要な節目や重要な到達点を示す時点",
            "ウ": "プロジェクトの日次の進捗報告を行う会議",
            "エ": "プロジェクトの最終成果物を示す文書"
        },
        "answer": "イ",
        "explanation": "マウルストーンは、プロジェクトの進捗における重要な節目や到達点のことです。「設計完了」「テスト開始」「リリース日」など、プロジェクトの重要なウベントや達成すべきポウントに設定されます。ガントチャート上では菱形記号で表示されることが多いです。"
    },
    {
        "id": "M038",
        "category": "マネジメント系",
        "subcategory": "システム監査",
        "topic": "システム監査",
        "difficulty": 2,
        "question": "システム監査の手順として、適切な順序はどれか。",
        "choices": {
            "ア": "監査計画→予備調査→本調査→監査報告→フォローアップ",
            "イ": "監査報告→監査計画→予備調査→本調査→フォローアップ",
            "ウ": "予備調査→監査計画→本調査→フォローアップ→監査報告",
            "エ": "本調査→予備調査→監査計画→監査報告→フォローアップ"
        },
        "answer": "ア",
        "explanation": "システム監査は、①監査計画（対象・方法の決定）→②予備調査（資料収集・ヒアリング）→③本調査（詳細な検証・評価）→④監査報告（結果の報告・改善勧告）→⑤フォローアップ（改善状況の確認）の手順で実施されます。"
    },
    {
        "id": "M039",
        "category": "マネジメント系",
        "subcategory": "開発技術",
        "topic": "システム開発技術",
        "difficulty": 2,
        "question": "回帰テスト（リグレッションテスト）の目的として、適切なものはどれか。",
        "choices": {
            "ア": "システムが最大負荷に耐えられるかを確認する。",
            "イ": "プログラムの変更によって、既存の機能が影響を受けていないことを確認する。",
            "ウ": "ユーザーインタフェースの使いやすさを確認する。",
            "エ": "セキュリティの脆弱性がないことを確認する。"
        },
        "answer": "イ",
        "explanation": "回帰テスト（リグレッションテスト）は、プログラムの修正や機能追加を行った後に、変更箇所以外の既存の機能が正常に動作するか（デグレード＝品質劣化が起きていないか）を確認するためのテストです。"
    },
    {
        "id": "M040",
        "category": "マネジメント系",
        "subcategory": "サービスマネジメント",
        "topic": "サービスの運用",
        "difficulty": 2,
        "question": "BCP（Business Continuity Plan：事業継続計画）の説明として、適切なものはどれか。",
        "choices": {
            "ア": "災害やシステム障害などの緊急事態が発生した場合に、事業の継続や早期復旧を図るための計画",
            "イ": "新規事業の立ち上げに必要な手順をまとめた計画",
            "ウ": "従業員の教育訓練計画をまとめた文書",
            "エ": "企業の年間の経営計画を策定する文書"
        },
        "answer": "ア",
        "explanation": "BCP（事業継続計画）は、地震・洪水などの自然災害、感染症の流行、大規模なシステム障害などの緊急事態に直面した場合に、重要な事業を中断させない、または中断しても可能な限り短い期間で復旧させるための計画です。"
    },
    {
        "id": "M041",
        "category": "マネジメント系",
        "subcategory": "プロジェクトマネジメント",
        "topic": "プロジェクトマネジメント手法",
        "difficulty": 2,
        "question": "KPI（Key Performance Indicator）の説明として、適切なものはどれか。",
        "choices": {
            "ア": "プロジェクトの完了条件を定義する文書",
            "イ": "プロジェクトメンバーの評価基準",
            "ウ": "目標の達成度合いを定量的に評価するための重要な指標",
            "エ": "システムの性能を測定するベンチマークツール"
        },
        "answer": "ウ",
        "explanation": "KPI（重要業績評価指標）は、組織やプロジェクトの目標達成度合いを定量的に評価するための重要な指標です。例えば「顧客満足度90%以上」「障害復旧時間30分以内」などが KPIとして設定されます。KGI（重要目標達成指標）の達成に向けた過程を測る中間指標です。"
    },
    {
        "id": "M042",
        "category": "マネジメント系",
        "subcategory": "開発技術",
        "topic": "システム開発技術",
        "difficulty": 2,
        "question": "UML（Unified Modeling Language）の説明として、適切なものはどれか。",
        "choices": {
            "ア": "人工知能の開発に特化したプログラミング言語",
            "イ": "ソフトウェアの設計や構造を視覚的に表現するための標準化されたモデリング言語",
            "ウ": "データベースを操作するための問合せ言語",
            "エ": "Webページを記述するためのマークアップ言語"
        },
        "answer": "イ",
        "explanation": "UML（統一モデリング言語）は、ソフトウェイの構造や振る舞いを図（ダエイグラム）で視覚的に表現するための標準化された表記法です。クラス図、ユースケース図、シーケンス図、イクティビティ図など、13種類の図が定義されています。"
    },
    {
        "id": "M043",
        "category": "マネジメント系",
        "subcategory": "システム監査",
        "topic": "内部統制",
        "difficulty": 2,
        "question": "職務の分離（職務分掌）が内部統制において重要とされる理由として、適切なものはどれか。",
        "choices": {
            "ア": "各担当者の作業量を均等にするため",
            "イ": "社員のスキル向上を促進するため",
            "ウ": "人件費を削減するため",
            "エ": "一人の担当者が不正を行う機会を減らし、相互牽制の仕組みを作るため"
        },
        "answer": "エ",
        "explanation": "職務分離（職務分掌）は、承認・実行・記録・保管などの業務を異なる担当者が行うようにすることで、一人の担当者による不正や誤りを防止する内部統制の基本原則です。例えば、発注と検収を同じ人が行わないようにします。"
    },
    {
        "id": "M044",
        "category": "マネジメント系",
        "subcategory": "開発技術",
        "topic": "ソフトウェア開発管理技術",
        "difficulty": 2,
        "question": "Git（ギット）などのバージョン管理システムの目的として、適切なものはどれか。",
        "choices": {
            "ア": "開発者のスケジュールを管理する。",
            "イ": "ソースコードの変更履歴を記録・管理し、複数人での共同開発を支援する。",
            "ウ": "プログラムの実行速度を最適化する。",
            "エ": "プログラムの脆弱性を自動的に検出する。"
        },
        "answer": "イ",
        "explanation": "バージョン管理システム（VCS）は、ファウルの変更履歴を記録し、特定の時点の状態に戻したり、複数人での並行開発を支援するツールです。Gitは最も広く使われている分散型バージョン管理システムで、ブランチやマージの機能が充実しています。"
    },
    {
        "id": "M045",
        "category": "マネジメント系",
        "subcategory": "サービスマネジメント",
        "topic": "サービスの運用",
        "difficulty": 2,
        "question": "サービスレベル管理の活動として、適切なものはどれか。",
        "choices": {
            "ア": "ネットワーク機器のIPアドレスを管理する。",
            "イ": "SLAで合意したサービス品質の目標値を監視し、達成状況を報告・改善する。",
            "ウ": "システム開発の工数を見積もる。",
            "エ": "データベースのバックアップスケジュールを作成する。"
        },
        "answer": "イ",
        "explanation": "サービスレベル管理は、SLA（サービスレベル合意書）で定義したサービスの品質目標（稼働率、応答時間など）を継続的に監視・測定し、目標の達成状況を報告するとともに、未達の場合は改善活動を実施するプロセスです。"
    },
    {
        "id": "M046",
        "category": "マネジメント系",
        "subcategory": "開発技術",
        "topic": "システム開発技術",
        "difficulty": 2,
        "question": "プロトタイピングモデルの特徴として、適切なものはどれか。",
        "choices": {
            "ア": "開発工程をスプリントと呼ばれる短い期間に分けて繰り返す。",
            "イ": "システムを独立した複数のサブシステムに分割し、並行して開発する。",
            "ウ": "各工程を上流から下流へ順番に進め、後戻りしない。",
            "エ": "試作品（プロトタイプ）を早期に作成し、ユーザーに確認してもらいながら開発を進める。"
        },
        "answer": "エ",
        "explanation": "プロトタウピングモデルは、開発の早い段階で試作品（プロトタウプ）を作成し、ユーザーに実際に操作してもらうことで要求を明確化し、完成品に近づけていく開発手法です。ユーザーの要求があいまいな場合に有効です。ウはイォータフォールモデルの特徴です。"
    },
    {
        "id": "M047",
        "category": "マネジメント系",
        "subcategory": "プロジェクトマネジメント",
        "topic": "プロジェクトマネジメント手法",
        "difficulty": 2,
        "question": "プロジェクト憲章（プロジェクトチャーター）の説明として、適切なものはどれか。",
        "choices": {
            "ア": "プロジェクトで使用する技術仕様を定義した文書",
            "イ": "プロジェクトの詳細なスケジュールを記載した文書",
            "ウ": "プロジェクト完了後の反省点をまとめた文書",
            "エ": "プロジェクトの目的、範囲、主要なステークホルダー、権限などを定義し、プロジェクトの開始を正式に承認する文書"
        },
        "answer": "エ",
        "explanation": "プロジェクト憲章（チャーター）は、プロジェクトの正式な開始を宣言する文書で、プロジェクトの目的、スコープ（範囲）、主要な成果物、プロジェクトマネージャーの任命と権限、予算の概要などが記載されます。スポンサーが承認します。"
    },
    {
        "id": "M048",
        "category": "マネジメント系",
        "subcategory": "サービスマネジメント",
        "topic": "ファシリティマネジメント",
        "difficulty": 2,
        "question": "ディザスタリカバリ（DR）の説明として、適切なものはどれか。",
        "choices": {
            "ア": "不正アクセスを検知して遮断するシステム",
            "イ": "システムのパフォーマンスを監視する仕組み",
            "ウ": "災害によりシステムが被害を受けた場合に、システムやデータを復旧するための計画や仕組み",
            "エ": "システムの脆弱性を事前に検出して対策する仕組み"
        },
        "answer": "ウ",
        "explanation": "ディザスタリカバリ（DR: Disaster Recovery）は、地震・洪水・火災などの災害によりITシステムが被害を受けた場合に、迅速にシステムを復旧させるための計画・手順・仕組みです。遠隔地にバックウップサエトを設ける方法が一般的です。"
    },
    {
        "id": "M049",
        "category": "マネジメント系",
        "subcategory": "開発技術",
        "topic": "システム開発技術",
        "difficulty": 2,
        "question": "カンバン方式のソフトウェア開発の特徴として、適切なものはどれか。",
        "choices": {
            "ア": "全工程を事前に詳細に計画してから開発に着手する手法",
            "イ": "一人の開発者がすべての工程を担当する手法",
            "ウ": "作業の流れを可視化し、進行中の作業数を制限することで効率を高める手法",
            "エ": "テストを自動化することに重点を置く手法"
        },
        "answer": "ウ",
        "explanation": "カンバン方式は、ボード上に「To Do（未着手）」「In Progress（進行中）」「Done（完了）」などの列を設けて作業の流れを可視化し、WIP（Work In Progress：仕掛り作業）の上限を設けることで、ボトルネックを発見し、作業の流れを改善する手法です。"
    },
    {
        "id": "M050",
        "category": "マネジメント系",
        "subcategory": "システム監査",
        "topic": "内部統制",
        "difficulty": 2,
        "question": "コンプライアンスの説明として、適切なものはどれか。",
        "choices": {
            "ア": "企業がコスト削減のために業務を外部委託すること",
            "イ": "企業が法令や社内規程、社会的規範を遵守して事業活動を行うこと",
            "ウ": "企業が新しい技術を研究開発すること",
            "エ": "企業が顧客満足度を向上させるための活動"
        },
        "answer": "イ",
        "explanation": "コンプラアインス（法令遵守）は、企業や組織が法律、規則、社内規程、企業倫理、社会的規範を遵守して事業活動を行うことです。コンプラアインス違反は企業の信頼失墜や法的制裁につながるため、内部統制の重要な要素です。"
    }
]